{
  "source": "concepts/05_power_systems/中壓電力引入.md",
  "md_hash": "3f25304953027c4b00aa1b3df446c26873ad11aa",
  "reviewed": true,
  "intel": [
    {
      "t": "概述",
      "intro": "大型 AIDC（ 10 MW）不可能以傳統低壓（380V/480V）直接從台電配電網取電——光是供應 100 MW 負載，以 380V 計算所需電流高達 152,000 A，完全不可行。因此，大型 AIDC 必須以中壓（11kV / 22kV）甚至超高壓（161kV）引入電力，在廠區內自建降壓系統。",
      "points": [
        "因此，大型 AIDC 必須以中壓（11kV / 22kV）甚至超高壓（161kV）引入電力，在廠區內自建降壓系統",
        "遵循 HVAC 與電力系統設計規範以提升 AIDC 可靠度"
      ],
      "f": "工程焦點：概述",
      "note": "工程評估：部署 中壓電力引入 (Medium Voltage Distribution) 時，必須對其 概述 的具體規格進行多重容錯認證。"
    },
    {
      "t": "1. 台電供電架構與 A...",
      "intro": "[台電超高壓系統 345kV / 161kV]",
      "points": [
        "掌握 1. 台電供電架構與 AIDC 電力引入層級 相關核心工程規格與技術引數",
        "注意在實際 AIDC 環控要求下的系統相容性調節"
      ],
      "f": "工程焦點：1. 台電供電架構與 AIDC 電力引入層級",
      "note": "台灣大型 AIDC 工程實務："
    },
    {
      "t": "2. 中壓配電的核心組件",
      "intro": "用戶端的第一個電力轉換點，包含：",
      "points": [
        "高壓斷路器（VCB, Vacuum Circuit Breaker）：常態導通，故障時極快切斷（< 3 個週期 = 60 ms）",
        "電壓互感器（VT/PT）與電流互感器（CT）：量測與保護用",
        "保護繼電器（Protection Relay）：偵測短路、接地、過電流，觸發 VCB 跳脫",
        "以 SF₆ 氣體（六氟化硫，絕緣性能是空氣的 2.5 倍）填充的密封金屬外殼"
      ],
      "f": "工程焦點：2. 中壓配電的核心組件",
      "note": "工程評估：部署 中壓電力引入 (Medium Voltage Distribution) 時，必須對其 2. 中壓配電的核心組件 的具體規格進行多重容錯認證。"
    },
    {
      "t": "3. 台電大容量用電申請流程",
      "intro": "AIDC 建置大量電力引入是高度受管制的程序，與台電的協商通常需要 18~36 個月：",
      "points": [
        "大型 AIDC 的電力需求申請可能面臨數年等待，或需配合台電新建電力基礎設施",
        "鴻海、廣達等廠商已提前數年佈局電力"
      ],
      "f": "工程焦點：3. 台電大容量用電申請流程",
      "note": "⚠️ 台灣電力供應瓶頸（2024~2030）： 台灣中北部電網容量緊張，部分縣市的 22kV 饋線出線容量已接近飽和。大型 AIDC 的電力需求申請可能面臨數年等待，或需配合台電新建電力基礎設施。鴻海、廣達等廠商已提前數年佈局電力。"
    }
  ],
  "questions": [
    {
      "id": "q1",
      "type": "single",
      "d": 1,
      "q": "當 AIDC 的電力總容量需求達到 20 MW 至 100 MW 以上時，為什麼無法直接以低壓（380V/480V）從公共配電網取電，而必須採用中壓（22kV / 11kV）甚至超高壓（161kV）引入？",
      "opts": [
        "因為低壓直流電在高溫下會自動轉化為高頻電磁波，干擾 GPU 叢集的心跳包通訊",
        "因為 100 MW 負載若以 380V 輸送，滿載電流將高達 152,000A。這需要直徑數公尺的巨大銅電纜，在工程與造價上完全不可能實現。採用高電壓引入可大幅降低輸電電流，使導線尺寸在可行範圍內",
        "因為台電法規規定，只有中壓以上的電力才能被冰水主機（Chiller）的壓縮機使用，低壓電只能供給風扇",
        "因為中壓電力具有「自冷特性」，電力在傳輸過程中會自動降溫，不需要機房空調進行熱補償"
      ],
      "ans": 1,
      "tag": "電力引入電壓等級選擇",
      "ex": "當功率達到數十 MW 時，如果電壓採用 380V，電流將達到十幾萬安培。這電線電纜將巨大無比且損耗極高。透過提升傳輸電壓（如台電 22kV 饋線或自建 161kV 受電站），電流可下降數十到數百倍，從而使用一般規格的進線電纜便能完成大容量電力傳輸。"
    },
    {
      "id": "q2",
      "type": "single",
      "d": 1,
      "q": "在都市型或土地昂貴區域建設 AIDC 時，中壓配電受電室為什麼通常會選用氣體絕緣開關設備（GIS）而非傳統的空氣絕緣開關設備（AIS）？",
      "opts": [
        "因為 GIS 內部填充了高溫柴油，可以在市電斷電時自動發電，省去發電機的建置",
        "因為 GIS 以 SF₆（六氟化硫）作為絕緣介質，其絕緣強度為空氣的 2.5 倍，可將受電開關設備的佔地體積縮小至傳統 AIS 的 1/5 ~ 1/10，能大幅節省昂貴的機房空間",
        "因為 GIS 可以直接安裝在冷凍水管路內部，藉由冰水將開關的發熱量完全降為零",
        "因為 GIS 設備完全不使用任何金屬材料，不易發生短路或電弧事故，維護成本為零"
      ],
      "ans": 1,
      "tag": "GIS 氣體絕緣開關特徵",
      "ex": "氣體絕緣開關設備（GIS）將斷路器、隔離開關、CT/PT 等封閉在金屬外殼內，並填充高絕緣強度的 SF₆（六氟化硫）氣體。這使得相間與對地安全距離大幅縮短，其體積僅為傳統空氣絕緣 AIS 的 10%~20%，對新竹或台北等土地與機房空間寸土寸金的 AIDC 來說，是節省空間的首選方案。"
    },
    {
      "id": "q3",
      "type": "single",
      "d": 2,
      "q": "在 AIDC 廠區內降壓配電變壓器的選型中，乾式變壓器（Dry-type）與油浸式變壓器（Oil-immersed）在安全規範、安裝位置與維護需求上存在何種差異？",
      "opts": [
        "乾式變壓器使用變壓器油冷卻，必須安裝在室外並設置防爆油坑；油浸式無油不易燃，可直接裝在 IT 白區內",
        "乾式變壓器以空氣對流冷卻，無油不易燃，防火安全性極佳，適合安裝在室內白區附近；油浸式容量大且效率略高，但變壓器油易燃，需設有油坑與防爆隔牆，通常裝在室外主變電站",
        "乾式變壓器的最高工作效率為 100%，而油浸式變壓器會因為油的熱阻使效率下降至 50% 以下",
        "兩者在結構與安全性上沒有任何區別，AIDC 僅因造價考量而混合使用"
      ],
      "ans": 1,
      "tag": "變壓器選型與安全",
      "ex": "乾式變壓器內部無易燃的變壓器油，沒有爆炸與火災風險，符合室內防火規範，常安裝在 IT 白區相鄰的單元變電站。油浸式變壓器則具有高容量、低造價、效率略佳的優點，但其礦物油屬易燃介質，一旦故障有起火爆炸風險，因此必須設有攔油坑與防火牆，通常佈置在室外的主受電站。"
    },
    {
      "id": "q4",
      "type": "single",
      "d": 2,
      "q": "為了實現 Uptime Tier III / Tier IV 規定的可靠性，中壓電力引入在饋線路由（Feeder Routes）與上游變電所（Substations）的配置上，有哪些嚴格的要求？",
      "opts": [
        "兩路中壓饋線必須綑綁在同一根電線桿上引入，以方便台電進行一次性檢修",
        "A/B 雙路中壓電源必須來自台電不同的變電所（或不同的獨立出線饋線大排），且兩路進線電纜必須走完全不同的物理路徑與管道，防止單點故障（如道路開挖挖斷）造成雙路同時中斷",
        "中壓饋線必須配備自動加水冷卻系統，且不允許通過任何斷路器（VCB）隔離",
        "Tier IV 要求中壓配電室必須與 IT 白區共用同一套高壓水霧滅火系統，且不設置防煙分區"
      ],
      "ans": 1,
      "tag": "雙路饋線與變援路由設計",
      "ex": "Tier III/IV 要求系統具備「同時可維護性」或「容錯性」。在中壓引入層面，A/B 雙路電源不可共用相同的物理路由，必須採用物理隔離的雙路由進線。更進一步，Tier IV 要求這兩路電力應來自不同的上游市電變電所，以排除單一變電站全站失電（Blackout）帶來的共模故障風險。"
    },
    {
      "id": "q5",
      "type": "single",
      "d": 3,
      "q": "【計算題】某 60 MW AIDC 專案，向台電申請 22 kV 中壓專線供電。已知該機房的功率因數 PF = 0.90。\n1. 請計算該機房在滿載運行時，台電 22 kV 進線端所需的輸入總視在功率為多少？進線三相電流為多少？\n2. 假設改用 161 kV 超高壓引入，在相同容量下，三相進線電流會降為多少？",
      "opts": [
        "22kV端：66.7 MVA，1,750 A；161kV端：239 A",
        "22kV端：66.7 MVA，1,750 A；161kV端：328 A",
        "22kV端：54.0 MVA，1,417 A；161kV端：194 A",
        "22kV端：66.7 MVA，3,030 A；161kV端：414 A"
      ],
      "ans": 0,
      "tag": "視在功率與引入電流計算",
      "ex": "計算步驟如下：\n1. 計算視在功率 S：S = 60 MW / 0.90 = 66.67 MVA。\n2. 22 kV 三相電流計算：I_22 = S / (√3 × V) = 66,666,667 VA / (1.732 × 22,000 V) ≈ 1,750 A。\n3. 161 kV 三相電流計算：I_161 = 66,666,667 VA / (1.732 × 161,000 V) ≈ 239 A。"
    },
    {
      "id": "q6",
      "type": "single",
      "d": 3,
      "q": "【計算題】某 AIDC 受電室之高壓真空斷路器（VCB），其標稱故障切斷時間為 3 個電網週期（在 60 Hz 交流電下）。若中壓變壓器內部突發三相短路故障，產生了 20 kA 的對稱短路電流。請問：\n1. VCB 從接收到繼電器跳脫信號到完全熄弧，需要多少毫秒？\n2. 在此切斷時間內，故障點所釋放的最大熱能量（I²t 值）為多少？",
      "opts": [
        "切斷時間 50 ms；I²t 值為 2.0 × 10^7 A²·s",
        "切斷時間 50 ms；I²t 值為 1.0 × 10^7 A²·s",
        "切斷時間 60 ms；I²t 值為 2.4 × 10^7 A²·s",
        "切斷時間 30 ms；I²t 值為 1.2 × 10^7 A²·s"
      ],
      "ans": 0,
      "tag": "斷路器動作時序與熱能量積算",
      "ex": "計算步驟如下：\n1. 60 Hz 電網單個週期時間 T = 1 / 60 秒 ≈ 16.67 ms。\n2. VCB 動作時間為 3 個週期：t = 3 × 16.67 = 50 ms = 0.05 秒。\n3. 計算 I²t 熱能積分值：I²t = (20,000 A)² × 0.05 s = 2.0 × 10^7 A²·s。"
    }
  ]
}